{ 
    "azure_appservice_site": {
      "aws": {},
      "gcp": {},
      "azure": {
        "subscriptionIdAttribute": "subscription_id"
      },
      "parsedAttributes": [
            {
                "sourceName":"extendedLocation",
                "targetName":"extended_location",
                "targetType":"TEXT",
                "enabled":true
            },
            {
                "sourceName":"extendedLocation_name",
                "targetName":"extended_location_name",
                "targetType":"TEXT",
                "enabled":true
            },
            {
                "sourceName":"extendedLocation_type",
                "targetName":"extended_location_type",
                "targetType":"TEXT",
                "enabled":true
            },
            {
                "sourceName":"id",
                "targetName":"id",
                "targetType":"TEXT",
                "enabled":true
            },
            {
                "sourceName":"identity",
                "targetName":"identity",
                "targetType":"TEXT",
                "enabled":true
            },
            {
                "sourceName":"identity_principalId",
                "targetName":"identity_principal_id",
                "targetType":"TEXT",
                "enabled":true
            },
            {
                "sourceName":"identity_tenantId",
                "targetName":"identity_tenant_id",
                "targetType":"TEXT",
                "enabled":true
            },
            {
                "sourceName":"identity_type",
                "targetName":"identity_type",
                "targetType":"TEXT",
                "enabled":true
            },
            {
                "sourceName":"identity_userAssignedIdentities",
                "targetName":"identity_user_assigned_identities",
                "targetType":"TEXT",
                "enabled":true
            },
            {
                "sourceName":"kind",
                "targetName":"kind",
                "targetType":"TEXT",
                "enabled":true
            },
            {
                "sourceName":"location",
                "targetName":"location",
                "targetType":"TEXT",
                "enabled":true
            },
            {
                "sourceName":"name",
                "targetName":"name",
                "targetType":"TEXT",
                "enabled":true
            },
            {
                "sourceName":"properties",
                "targetName":"properties",
                "targetType":"TEXT",
                "enabled":true
            },
            {
                "sourceName":"properties_availabilityState",
                "targetName":"availability_state",
                "targetType":"TEXT",
                "enabled":true
            },
            {
                "sourceName":"properties_clientAffinityEnabled",
                "targetName":"client_affinity_enabled",
                "targetType":"TEXT",
                "enabled":true
            },
            {
                "sourceName":"properties_clientCertEnabled",
                "targetName":"client_cert_enabled",
                "targetType":"TEXT",
                "enabled":true
            },
            {
                "sourceName":"properties_clientCertExclusionPaths",
                "targetName":"client_cert_exclusion_paths",
                "targetType":"TEXT",
                "enabled":true
            },
            {
                "sourceName":"properties_clientCertMode",
                "targetName":"client_cert_mode",
                "targetType":"TEXT",
                "enabled":true
            },
            {
                "sourceName":"properties_cloningInfo",
                "targetName":"cloning_info",
                "targetType":"TEXT",
                "enabled":true
            },
            {
                "sourceName":"properties_cloningInfo_appSettingsOverrides",
                "targetName":"cloning_info_app_settings_overrides",
                "targetType":"TEXT",
                "enabled":false
            },
            {
                "sourceName":"properties_cloningInfo_cloneCustomHostNames",
                "targetName":"cloning_info_clone_custom_host_names",
                "targetType":"TEXT",
                "enabled":false
            },
            {
                "sourceName":"properties_cloningInfo_cloneSourceControl",
                "targetName":"cloning_info_clone_source_control",
                "targetType":"TEXT",
                "enabled":false
            },
            {
                "sourceName":"properties_cloningInfo_configureLoadBalancing",
                "targetName":"cloning_info_configure_load_balancing",
                "targetType":"TEXT",
                "enabled":false
            },
            {
                "sourceName":"properties_cloningInfo_correlationId",
                "targetName":"cloning_info_correlation_id",
                "targetType":"TEXT",
                "enabled":false
            },
            {
                "sourceName":"properties_cloningInfo_hostingEnvironment",
                "targetName":"cloning_info_hosting_environment",
                "targetType":"TEXT",
                "enabled":false
            },
            {
                "sourceName":"properties_cloningInfo_overwrite",
                "targetName":"cloning_info_overwrite",
                "targetType":"TEXT",
                "enabled":false
            },
            {
                "sourceName":"properties_cloningInfo_sourceWebAppId",
                "targetName":"cloning_info_source_web_app_id",
                "targetType":"TEXT",
                "enabled":false
            },
            {
                "sourceName":"properties_cloningInfo_sourceWebAppLocation",
                "targetName":"cloning_info_source_web_app_location",
                "targetType":"TEXT",
                "enabled":false
            },
            {
                "sourceName":"properties_cloningInfo_trafficManagerProfileId",
                "targetName":"cloning_info_traffic_manager_profile_id",
                "targetType":"TEXT",
                "enabled":false
            },
            {
                "sourceName":"properties_cloningInfo_trafficManagerProfileName",
                "targetName":"cloning_info_traffic_manager_profile_name",
                "targetType":"TEXT",
                "enabled":false
            },
            {
                "sourceName":"properties_containerSize",
                "targetName":"container_size",
                "targetType":"INTEGER",
                "enabled":true
            },
            {
                "sourceName":"properties_customDomainVerificationId",
                "targetName":"custom_domain_verification_id",
                "targetType":"TEXT",
                "enabled":true
            },
            {
                "sourceName":"properties_dailyMemoryTimeQuota",
                "targetName":"daily_memory_time_quota",
                "targetType":"INTEGER",
                "enabled":true
            },
            {
                "sourceName":"properties_defaultHostName",
                "targetName":"default_host_name",
                "targetType":"TEXT",
                "enabled":true
            },
            {
                "sourceName":"properties_enabled",
                "targetName":"enabled",
                "targetType":"TEXT",
                "enabled":true
            },
            {
                "sourceName":"properties_enabledHostNames",
                "targetName":"enabled_host_names",
                "targetType":"TEXT",
                "enabled":true
            },
            {
                "sourceName":"properties_hostNameSslStates",
                "targetName":"host_name_ssl_states",
                "targetType":"TEXT",
                "enabled":true
            },
            {
                "sourceName":"properties_hostNameSslStates_hostType",
                "targetName":"host_name_ssl_states_host_type",
                "targetType":"TEXT",
                "enabled":false
            },
            {
                "sourceName":"properties_hostNameSslStates_name",
                "targetName":"host_name_ssl_states_name",
                "targetType":"TEXT",
                "enabled":false
            },
            {
                "sourceName":"properties_hostNameSslStates_sslState",
                "targetName":"host_name_ssl_states_ssl_state",
                "targetType":"TEXT",
                "enabled":false
            },
            {
                "sourceName":"properties_hostNameSslStates_thumbprint",
                "targetName":"host_name_ssl_states_thumbprint",
                "targetType":"TEXT",
                "enabled":false
            },
            {
                "sourceName":"properties_hostNameSslStates_toUpdate",
                "targetName":"host_name_ssl_states_to_update",
                "targetType":"TEXT",
                "enabled":false
            },
            {
                "sourceName":"properties_hostNameSslStates_virtualIP",
                "targetName":"host_name_ssl_states_virtual_ip",
                "targetType":"TEXT",
                "enabled":false
            },
            {
                "sourceName":"properties_hostNames",
                "targetName":"host_names",
                "targetType":"TEXT",
                "enabled":true
            },
            {
                "sourceName":"properties_hostNamesDisabled",
                "targetName":"host_names_disabled",
                "targetType":"TEXT",
                "enabled":true
            },
            {
                "sourceName":"properties_hostingEnvironmentProfile",
                "targetName":"hosting_environment_profile",
                "targetType":"TEXT",
                "enabled":true
            },
            {
                "sourceName":"properties_hostingEnvironmentProfile_id",
                "targetName":"hosting_environment_profile_id",
                "targetType":"TEXT",
                "enabled":false
            },
            {
                "sourceName":"properties_hostingEnvironmentProfile_name",
                "targetName":"hosting_environment_profile_name",
                "targetType":"TEXT",
                "enabled":false
            },
            {
                "sourceName":"properties_hostingEnvironmentProfile_type",
                "targetName":"hosting_environment_profile_type",
                "targetType":"TEXT",
                "enabled":false
            },
            {
                "sourceName":"properties_httpsOnly",
                "targetName":"https_only",
                "targetType":"TEXT",
                "enabled":true
            },
            {
                "sourceName":"properties_hyperV",
                "targetName":"hyper_v",
                "targetType":"TEXT",
                "enabled":true
            },
            {
                "sourceName":"properties_inProgressOperationId",
                "targetName":"in_progress_operation_id",
                "targetType":"TEXT",
                "enabled":true
            },
            {
                "sourceName":"properties_isDefaultContainer",
                "targetName":"is_default_container",
                "targetType":"TEXT",
                "enabled":true
            },
            {
                "sourceName":"properties_isXenon",
                "targetName":"is_xenon",
                "targetType":"TEXT",
                "enabled":true
            },
            {
                "sourceName":"properties_keyVaultReferenceIdentity",
                "targetName":"key_vault_reference_identity",
                "targetType":"TEXT",
                "enabled":true
            },
            {
                "sourceName":"properties_lastModifiedTimeUtc",
                "targetName":"last_modified_time_utc",
                "targetType":"TEXT",
                "enabled":true
            },
            {
                "sourceName":"properties_maxNumberOfWorkers",
                "targetName":"max_number_of_workers",
                "targetType":"INTEGER",
                "enabled":true
            },
            {
                "sourceName":"properties_outboundIpAddresses",
                "targetName":"outbound_ip_addresses",
                "targetType":"TEXT",
                "enabled":true
            },
            {
                "sourceName":"properties_possibleOutboundIpAddresses",
                "targetName":"possible_outbound_ip_addresses",
                "targetType":"TEXT",
                "enabled":true
            },
            {
                "sourceName":"properties_redundancyMode",
                "targetName":"redundancy_mode",
                "targetType":"TEXT",
                "enabled":true
            },
            {
                "sourceName":"properties_repositorySiteName",
                "targetName":"repository_site_name",
                "targetType":"TEXT",
                "enabled":true
            },
            {
                "sourceName":"properties_reserved",
                "targetName":"reserved",
                "targetType":"TEXT",
                "enabled":true
            },
            {
                "sourceName":"properties_resourceGroup",
                "targetName":"resource_group",
                "targetType":"TEXT",
                "enabled":true
            },
            {
                "sourceName":"properties_scmSiteAlsoStopped",
                "targetName":"scm_site_also_stopped",
                "targetType":"TEXT",
                "enabled":true
            },
            {
                "sourceName":"properties_serverFarmId",
                "targetName":"server_farm_id",
                "targetType":"TEXT",
                "enabled":true
            },
            {
                "sourceName":"properties_siteConfig",
                "targetName":"site_config",
                "targetType":"TEXT",
                "enabled":true
            },
            {
                "sourceName":"properties_siteConfig_acrUseManagedIdentityCreds",
                "targetName":"site_config_acr_use_managed_identity_creds",
                "targetType":"TEXT",
                "enabled":false
            },
            {
                "sourceName":"properties_siteConfig_acrUserManagedIdentityID",
                "targetName":"site_config_acr_user_managed_identity_id",
                "targetType":"TEXT",
                "enabled":false
            },
            {
                "sourceName":"properties_siteConfig_alwaysOn",
                "targetName":"site_config_always_on",
                "targetType":"TEXT",
                "enabled":false
            },
            {
                "sourceName":"properties_siteConfig_apiDefinition",
                "targetName":"site_config_api_definition",
                "targetType":"TEXT",
                "enabled":false
            },
            {
                "sourceName":"properties_siteConfig_apiDefinition_url",
                "targetName":"site_config_api_definition_url",
                "targetType":"TEXT",
                "enabled":false
            },
            {
                "sourceName":"properties_siteConfig_apiManagementConfig",
                "targetName":"site_config_api_management_config",
                "targetType":"TEXT",
                "enabled":false
            },
            {
                "sourceName":"properties_siteConfig_apiManagementConfig_id",
                "targetName":"site_config_api_management_config_id",
                "targetType":"TEXT",
                "enabled":false
            },
            {
                "sourceName":"properties_siteConfig_appCommandLine",
                "targetName":"site_config_app_command_line",
                "targetType":"TEXT",
                "enabled":false
            },
            {
                "sourceName":"properties_siteConfig_appSettings",
                "targetName":"site_config_app_settings",
                "targetType":"TEXT",
                "enabled":false
            },
            {
                "sourceName":"properties_siteConfig_appSettings_name",
                "targetName":"site_config_app_settings_name",
                "targetType":"TEXT",
                "enabled":false
            },
            {
                "sourceName":"properties_siteConfig_appSettings_value",
                "targetName":"site_config_app_settings_value",
                "targetType":"TEXT",
                "enabled":false
            },
            {
                "sourceName":"properties_siteConfig_autoHealEnabled",
                "targetName":"site_config_auto_heal_enabled",
                "targetType":"TEXT",
                "enabled":false
            },
            {
                "sourceName":"properties_siteConfig_autoHealRules",
                "targetName":"site_config_auto_heal_rules",
                "targetType":"TEXT",
                "enabled":false
            },
            {
                "sourceName":"properties_siteConfig_autoHealRules_actions",
                "targetName":"site_config_auto_heal_rules_actions",
                "targetType":"TEXT",
                "enabled":false
            },
            {
                "sourceName":"properties_siteConfig_autoHealRules_actions_actionType",
                "targetName":"site_config_auto_heal_rules_actions_action_type",
                "targetType":"TEXT",
                "enabled":false
            },
            {
                "sourceName":"properties_siteConfig_autoHealRules_actions_customAction",
                "targetName":"site_config_auto_heal_rules_actions_custom_action",
                "targetType":"TEXT",
                "enabled":false
            },
            {
                "sourceName":"properties_siteConfig_autoHealRules_actions_customAction_exe",
                "targetName":"site_config_auto_heal_rules_actions_custom_action_exe",
                "targetType":"TEXT",
                "enabled":false
            },
            {
                "sourceName":"properties_siteConfig_autoHealRules_actions_customAction_parameters",
                "targetName":"site_config_auto_heal_rules_actions_custom_action_parameters",
                "targetType":"TEXT",
                "enabled":false
            },
            {
                "sourceName":"properties_siteConfig_autoHealRules_actions_minProcessExecutionTime",
                "targetName":"site_config_auto_heal_rules_actions_min_process_execution_time",
                "targetType":"TEXT",
                "enabled":false
            },
            {
                "sourceName":"properties_siteConfig_autoHealRules_triggers",
                "targetName":"site_config_auto_heal_rules_triggers",
                "targetType":"TEXT",
                "enabled":false
            },
            {
                "sourceName":"properties_siteConfig_autoHealRules_triggers_privateBytesInKB",
                "targetName":"site_config_auto_heal_rules_triggers_private_bytes_in_kb",
                "targetType":"INTEGER",
                "enabled":false
            },
            {
                "sourceName":"properties_siteConfig_autoHealRules_triggers_requests",
                "targetName":"site_config_auto_heal_rules_triggers_requests",
                "targetType":"TEXT",
                "enabled":false
            },
            {
                "sourceName":"properties_siteConfig_autoHealRules_triggers_requests_count",
                "targetName":"site_config_auto_heal_rules_triggers_requests_count",
                "targetType":"INTEGER",
                "enabled":false
            },
            {
                "sourceName":"properties_siteConfig_autoHealRules_triggers_requests_timeInterval",
                "targetName":"site_config_auto_heal_rules_triggers_requests_time_interval",
                "targetType":"TEXT",
                "enabled":false
            },
            {
                "sourceName":"properties_siteConfig_autoHealRules_triggers_slowRequests",
                "targetName":"site_config_auto_heal_rules_triggers_slow_requests",
                "targetType":"TEXT",
                "enabled":false
            },
            {
                "sourceName":"properties_siteConfig_autoHealRules_triggers_slowRequestsWithPath",
                "targetName":"site_config_auto_heal_rules_triggers_slow_requests_with_path",
                "targetType":"TEXT",
                "enabled":false
            },
            {
                "sourceName":"properties_siteConfig_autoHealRules_triggers_slowRequestsWithPath_count",
                "targetName":"site_config_auto_heal_rules_triggers_slow_requests_with_path_count",
                "targetType":"INTEGER",
                "enabled":false
            },
            {
                "sourceName":"properties_siteConfig_autoHealRules_triggers_slowRequestsWithPath_path",
                "targetName":"site_config_auto_heal_rules_triggers_slow_requests_with_path_path",
                "targetType":"TEXT",
                "enabled":false
            },
            {
                "sourceName":"properties_siteConfig_autoHealRules_triggers_slowRequestsWithPath_timeInterval",
                "targetName":"site_config_auto_heal_rules_triggers_slow_requests_with_path_time_interval",
                "targetType":"TEXT",
                "enabled":false
            },
            {
                "sourceName":"properties_siteConfig_autoHealRules_triggers_slowRequestsWithPath_timeTaken",
                "targetName":"site_config_auto_heal_rules_triggers_slow_requests_with_path_time_taken",
                "targetType":"TEXT",
                "enabled":false
            },
            {
                "sourceName":"properties_siteConfig_autoHealRules_triggers_slowRequests_count",
                "targetName":"site_config_auto_heal_rules_triggers_slow_requests_count",
                "targetType":"INTEGER",
                "enabled":false
            },
            {
                "sourceName":"properties_siteConfig_autoHealRules_triggers_slowRequests_path",
                "targetName":"site_config_auto_heal_rules_triggers_slow_requests_path",
                "targetType":"TEXT",
                "enabled":false
            },
            {
                "sourceName":"properties_siteConfig_autoHealRules_triggers_slowRequests_timeInterval",
                "targetName":"site_config_auto_heal_rules_triggers_slow_requests_time_interval",
                "targetType":"TEXT",
                "enabled":false
            },
            {
                "sourceName":"properties_siteConfig_autoHealRules_triggers_slowRequests_timeTaken",
                "targetName":"site_config_auto_heal_rules_triggers_slow_requests_time_taken",
                "targetType":"TEXT",
                "enabled":false
            },
            {
                "sourceName":"properties_siteConfig_autoHealRules_triggers_statusCodes",
                "targetName":"site_config_auto_heal_rules_triggers_status_codes",
                "targetType":"TEXT",
                "enabled":false
            },
            {
                "sourceName":"properties_siteConfig_autoHealRules_triggers_statusCodesRange",
                "targetName":"site_config_auto_heal_rules_triggers_status_codes_range",
                "targetType":"TEXT",
                "enabled":false
            },
            {
                "sourceName":"properties_siteConfig_autoHealRules_triggers_statusCodesRange_count",
                "targetName":"site_config_auto_heal_rules_triggers_status_codes_range_count",
                "targetType":"INTEGER",
                "enabled":false
            },
            {
                "sourceName":"properties_siteConfig_autoHealRules_triggers_statusCodesRange_path",
                "targetName":"site_config_auto_heal_rules_triggers_status_codes_range_path",
                "targetType":"TEXT",
                "enabled":false
            },
            {
                "sourceName":"properties_siteConfig_autoHealRules_triggers_statusCodesRange_statusCodes",
                "targetName":"site_config_auto_heal_rules_triggers_status_codes_range_status_codes",
                "targetType":"TEXT",
                "enabled":false
            },
            {
                "sourceName":"properties_siteConfig_autoHealRules_triggers_statusCodesRange_timeInterval",
                "targetName":"site_config_auto_heal_rules_triggers_status_codes_range_time_interval",
                "targetType":"TEXT",
                "enabled":false
            },
            {
                "sourceName":"properties_siteConfig_autoHealRules_triggers_statusCodes_count",
                "targetName":"site_config_auto_heal_rules_triggers_status_codes_count",
                "targetType":"INTEGER",
                "enabled":false
            },
            {
                "sourceName":"properties_siteConfig_autoHealRules_triggers_statusCodes_path",
                "targetName":"site_config_auto_heal_rules_triggers_status_codes_path",
                "targetType":"TEXT",
                "enabled":false
            },
            {
                "sourceName":"properties_siteConfig_autoHealRules_triggers_statusCodes_status",
                "targetName":"site_config_auto_heal_rules_triggers_status_codes_status",
                "targetType":"INTEGER",
                "enabled":false
            },
            {
                "sourceName":"properties_siteConfig_autoHealRules_triggers_statusCodes_subStatus",
                "targetName":"site_config_auto_heal_rules_triggers_status_codes_sub_status",
                "targetType":"INTEGER",
                "enabled":false
            },
            {
                "sourceName":"properties_siteConfig_autoHealRules_triggers_statusCodes_timeInterval",
                "targetName":"site_config_auto_heal_rules_triggers_status_codes_time_interval",
                "targetType":"TEXT",
                "enabled":false
            },
            {
                "sourceName":"properties_siteConfig_autoHealRules_triggers_statusCodes_win32Status",
                "targetName":"site_config_auto_heal_rules_triggers_status_codes_win32_status",
                "targetType":"INTEGER",
                "enabled":false
            },
            {
                "sourceName":"properties_siteConfig_autoSwapSlotName",
                "targetName":"site_config_auto_swap_slot_name",
                "targetType":"TEXT",
                "enabled":false
            },
            {
                "sourceName":"properties_siteConfig_azureStorageAccounts",
                "targetName":"site_config_azure_storage_accounts",
                "targetType":"TEXT",
                "enabled":false
            },
            {
                "sourceName":"properties_siteConfig_connectionStrings",
                "targetName":"site_config_connection_strings",
                "targetType":"TEXT",
                "enabled":false
            },
            {
                "sourceName":"properties_siteConfig_connectionStrings_connectionString",
                "targetName":"site_config_connection_strings_connection_string",
                "targetType":"TEXT",
                "enabled":false
            },
            {
                "sourceName":"properties_siteConfig_connectionStrings_name",
                "targetName":"site_config_connection_strings_name",
                "targetType":"TEXT",
                "enabled":false
            },
            {
                "sourceName":"properties_siteConfig_connectionStrings_type",
                "targetName":"site_config_connection_strings_type",
                "targetType":"TEXT",
                "enabled":false
            },
            {
                "sourceName":"properties_siteConfig_cors",
                "targetName":"site_config_cors",
                "targetType":"TEXT",
                "enabled":false
            },
            {
                "sourceName":"properties_siteConfig_cors_allowedOrigins",
                "targetName":"site_config_cors_allowed_origins",
                "targetType":"TEXT",
                "enabled":false
            },
            {
                "sourceName":"properties_siteConfig_cors_supportCredentials",
                "targetName":"site_config_cors_support_credentials",
                "targetType":"TEXT",
                "enabled":false
            },
            {
                "sourceName":"properties_siteConfig_defaultDocuments",
                "targetName":"site_config_default_documents",
                "targetType":"TEXT",
                "enabled":false
            },
            {
                "sourceName":"properties_siteConfig_detailedErrorLoggingEnabled",
                "targetName":"site_config_detailed_error_logging_enabled",
                "targetType":"TEXT",
                "enabled":false
            },
            {
                "sourceName":"properties_siteConfig_documentRoot",
                "targetName":"site_config_document_root",
                "targetType":"TEXT",
                "enabled":false
            },
            {
                "sourceName":"properties_siteConfig_experiments",
                "targetName":"site_config_experiments",
                "targetType":"TEXT",
                "enabled":false
            },
            {
                "sourceName":"properties_siteConfig_experiments_rampUpRules",
                "targetName":"site_config_experiments_ramp_up_rules",
                "targetType":"TEXT",
                "enabled":false
            },
            {
                "sourceName":"properties_siteConfig_experiments_rampUpRules_actionHostName",
                "targetName":"site_config_experiments_ramp_up_rules_action_host_name",
                "targetType":"TEXT",
                "enabled":false
            },
            {
                "sourceName":"properties_siteConfig_experiments_rampUpRules_changeDecisionCallbackUrl",
                "targetName":"site_config_experiments_ramp_up_rules_change_decision_callback_url",
                "targetType":"TEXT",
                "enabled":false
            },
            {
                "sourceName":"properties_siteConfig_experiments_rampUpRules_changeIntervalInMinutes",
                "targetName":"site_config_experiments_ramp_up_rules_change_interval_in_minutes",
                "targetType":"INTEGER",
                "enabled":false
            },
            {
                "sourceName":"properties_siteConfig_experiments_rampUpRules_changeStep",
                "targetName":"site_config_experiments_ramp_up_rules_change_step",
                "targetType":"DOUBLE",
                "enabled":false
            },
            {
                "sourceName":"properties_siteConfig_experiments_rampUpRules_maxReroutePercentage",
                "targetName":"site_config_experiments_ramp_up_rules_max_reroute_percentage",
                "targetType":"DOUBLE",
                "enabled":false
            },
            {
                "sourceName":"properties_siteConfig_experiments_rampUpRules_minReroutePercentage",
                "targetName":"site_config_experiments_ramp_up_rules_min_reroute_percentage",
                "targetType":"DOUBLE",
                "enabled":false
            },
            {
                "sourceName":"properties_siteConfig_experiments_rampUpRules_name",
                "targetName":"site_config_experiments_ramp_up_rules_name",
                "targetType":"TEXT",
                "enabled":false
            },
            {
                "sourceName":"properties_siteConfig_experiments_rampUpRules_reroutePercentage",
                "targetName":"site_config_experiments_ramp_up_rules_reroute_percentage",
                "targetType":"DOUBLE",
                "enabled":false
            },
            {
                "sourceName":"properties_siteConfig_ftpsState",
                "targetName":"site_config_ftps_state",
                "targetType":"TEXT",
                "enabled":false
            },
            {
                "sourceName":"properties_siteConfig_functionAppScaleLimit",
                "targetName":"site_config_function_app_scale_limit",
                "targetType":"INTEGER",
                "enabled":false
            },
            {
                "sourceName":"properties_siteConfig_functionsRuntimeScaleMonitoringEnabled",
                "targetName":"site_config_functions_runtime_scale_monitoring_enabled",
                "targetType":"TEXT",
                "enabled":false
            },
            {
                "sourceName":"properties_siteConfig_handlerMappings",
                "targetName":"site_config_handler_mappings",
                "targetType":"TEXT",
                "enabled":false
            },
            {
                "sourceName":"properties_siteConfig_handlerMappings_arguments",
                "targetName":"site_config_handler_mappings_arguments",
                "targetType":"TEXT",
                "enabled":false
            },
            {
                "sourceName":"properties_siteConfig_handlerMappings_extension",
                "targetName":"site_config_handler_mappings_extension",
                "targetType":"TEXT",
                "enabled":false
            },
            {
                "sourceName":"properties_siteConfig_handlerMappings_scriptProcessor",
                "targetName":"site_config_handler_mappings_script_processor",
                "targetType":"TEXT",
                "enabled":false
            },
            {
                "sourceName":"properties_siteConfig_healthCheckPath",
                "targetName":"site_config_health_check_path",
                "targetType":"TEXT",
                "enabled":false
            },
            {
                "sourceName":"properties_siteConfig_http20Enabled",
                "targetName":"site_config_http20_enabled",
                "targetType":"TEXT",
                "enabled":false
            },
            {
                "sourceName":"properties_siteConfig_httpLoggingEnabled",
                "targetName":"site_config_http_logging_enabled",
                "targetType":"TEXT",
                "enabled":false
            },
            {
                "sourceName":"properties_siteConfig_ipSecurityRestrictions",
                "targetName":"site_config_ip_security_restrictions",
                "targetType":"TEXT",
                "enabled":false
            },
            {
                "sourceName":"properties_siteConfig_ipSecurityRestrictions_action",
                "targetName":"site_config_ip_security_restrictions_action",
                "targetType":"TEXT",
                "enabled":false
            },
            {
                "sourceName":"properties_siteConfig_ipSecurityRestrictions_description",
                "targetName":"site_config_ip_security_restrictions_description",
                "targetType":"TEXT",
                "enabled":false
            },
            {
                "sourceName":"properties_siteConfig_ipSecurityRestrictions_headers",
                "targetName":"site_config_ip_security_restrictions_headers",
                "targetType":"TEXT",
                "enabled":false
            },
            {
                "sourceName":"properties_siteConfig_ipSecurityRestrictions_ipAddress",
                "targetName":"site_config_ip_security_restrictions_ip_address",
                "targetType":"TEXT",
                "enabled":false
            },
            {
                "sourceName":"properties_siteConfig_ipSecurityRestrictions_name",
                "targetName":"site_config_ip_security_restrictions_name",
                "targetType":"TEXT",
                "enabled":false
            },
            {
                "sourceName":"properties_siteConfig_ipSecurityRestrictions_priority",
                "targetName":"site_config_ip_security_restrictions_priority",
                "targetType":"INTEGER",
                "enabled":false
            },
            {
                "sourceName":"properties_siteConfig_ipSecurityRestrictions_subnetMask",
                "targetName":"site_config_ip_security_restrictions_subnet_mask",
                "targetType":"TEXT",
                "enabled":false
            },
            {
                "sourceName":"properties_siteConfig_ipSecurityRestrictions_subnetTrafficTag",
                "targetName":"site_config_ip_security_restrictions_subnet_traffic_tag",
                "targetType":"INTEGER",
                "enabled":false
            },
            {
                "sourceName":"properties_siteConfig_ipSecurityRestrictions_tag",
                "targetName":"site_config_ip_security_restrictions_tag",
                "targetType":"TEXT",
                "enabled":false
            },
            {
                "sourceName":"properties_siteConfig_ipSecurityRestrictions_vnetSubnetResourceId",
                "targetName":"site_config_ip_security_restrictions_vnet_subnet_resource_id",
                "targetType":"TEXT",
                "enabled":false
            },
            {
                "sourceName":"properties_siteConfig_ipSecurityRestrictions_vnetTrafficTag",
                "targetName":"site_config_ip_security_restrictions_vnet_traffic_tag",
                "targetType":"INTEGER",
                "enabled":false
            },
            {
                "sourceName":"properties_siteConfig_javaContainer",
                "targetName":"site_config_java_container",
                "targetType":"TEXT",
                "enabled":false
            },
            {
                "sourceName":"properties_siteConfig_javaContainerVersion",
                "targetName":"site_config_java_container_version",
                "targetType":"TEXT",
                "enabled":false
            },
            {
                "sourceName":"properties_siteConfig_javaVersion",
                "targetName":"site_config_java_version",
                "targetType":"TEXT",
                "enabled":false
            },
            {
                "sourceName":"properties_siteConfig_keyVaultReferenceIdentity",
                "targetName":"site_config_key_vault_reference_identity",
                "targetType":"TEXT",
                "enabled":false
            },
            {
                "sourceName":"properties_siteConfig_limits",
                "targetName":"site_config_limits",
                "targetType":"TEXT",
                "enabled":false
            },
            {
                "sourceName":"properties_siteConfig_limits_maxDiskSizeInMb",
                "targetName":"site_config_limits_max_disk_size_in_mb",
                "targetType":"BIGINT",
                "enabled":false
            },
            {
                "sourceName":"properties_siteConfig_limits_maxMemoryInMb",
                "targetName":"site_config_limits_max_memory_in_mb",
                "targetType":"BIGINT",
                "enabled":false
            },
            {
                "sourceName":"properties_siteConfig_limits_maxPercentageCpu",
                "targetName":"site_config_limits_max_percentage_cpu",
                "targetType":"DOUBLE",
                "enabled":false
            },
            {
                "sourceName":"properties_siteConfig_linuxFxVersion",
                "targetName":"site_config_linux_fx_version",
                "targetType":"TEXT",
                "enabled":false
            },
            {
                "sourceName":"properties_siteConfig_loadBalancing",
                "targetName":"site_config_load_balancing",
                "targetType":"TEXT",
                "enabled":false
            },
            {
                "sourceName":"properties_siteConfig_localMySqlEnabled",
                "targetName":"site_config_local_my_sql_enabled",
                "targetType":"TEXT",
                "enabled":false
            },
            {
                "sourceName":"properties_siteConfig_logsDirectorySizeLimit",
                "targetName":"site_config_logs_directory_size_limit",
                "targetType":"INTEGER",
                "enabled":false
            },
            {
                "sourceName":"properties_siteConfig_machineKey",
                "targetName":"site_config_machine_key",
                "targetType":"TEXT",
                "enabled":false
            },
            {
                "sourceName":"properties_siteConfig_machineKey_decryption",
                "targetName":"site_config_machine_key_decryption",
                "targetType":"TEXT",
                "enabled":false
            },
            {
                "sourceName":"properties_siteConfig_machineKey_decryptionKey",
                "targetName":"site_config_machine_key_decryption_key",
                "targetType":"TEXT",
                "enabled":false
            },
            {
                "sourceName":"properties_siteConfig_machineKey_validation",
                "targetName":"site_config_machine_key_validation",
                "targetType":"TEXT",
                "enabled":false
            },
            {
                "sourceName":"properties_siteConfig_machineKey_validationKey",
                "targetName":"site_config_machine_key_validation_key",
                "targetType":"TEXT",
                "enabled":false
            },
            {
                "sourceName":"properties_siteConfig_managedPipelineMode",
                "targetName":"site_config_managed_pipeline_mode",
                "targetType":"TEXT",
                "enabled":false
            },
            {
                "sourceName":"properties_siteConfig_managedServiceIdentityId",
                "targetName":"site_config_managed_service_identity_id",
                "targetType":"INTEGER",
                "enabled":false
            },
            {
                "sourceName":"properties_siteConfig_minTlsVersion",
                "targetName":"site_config_min_tls_version",
                "targetType":"TEXT",
                "enabled":false
            },
            {
                "sourceName":"properties_siteConfig_minimumElasticInstanceCount",
                "targetName":"site_config_minimum_elastic_instance_count",
                "targetType":"INTEGER",
                "enabled":false
            },
            {
                "sourceName":"properties_siteConfig_netFrameworkVersion",
                "targetName":"site_config_net_framework_version",
                "targetType":"TEXT",
                "enabled":false
            },
            {
                "sourceName":"properties_siteConfig_nodeVersion",
                "targetName":"site_config_node_version",
                "targetType":"TEXT",
                "enabled":false
            },
            {
                "sourceName":"properties_siteConfig_numberOfWorkers",
                "targetName":"site_config_number_of_workers",
                "targetType":"INTEGER",
                "enabled":false
            },
            {
                "sourceName":"properties_siteConfig_phpVersion",
                "targetName":"site_config_php_version",
                "targetType":"TEXT",
                "enabled":false
            },
            {
                "sourceName":"properties_siteConfig_powerShellVersion",
                "targetName":"site_config_power_shell_version",
                "targetType":"TEXT",
                "enabled":false
            },
            {
                "sourceName":"properties_siteConfig_preWarmedInstanceCount",
                "targetName":"site_config_pre_warmed_instance_count",
                "targetType":"INTEGER",
                "enabled":false
            },
            {
                "sourceName":"properties_siteConfig_publicNetworkAccess",
                "targetName":"site_config_public_network_access",
                "targetType":"TEXT",
                "enabled":false
            },
            {
                "sourceName":"properties_siteConfig_publishingUsername",
                "targetName":"site_config_publishing_username",
                "targetType":"TEXT",
                "enabled":false
            },
            {
                "sourceName":"properties_siteConfig_push",
                "targetName":"site_config_push",
                "targetType":"TEXT",
                "enabled":false
            },
            {
                "sourceName":"properties_siteConfig_push_id",
                "targetName":"site_config_push_id",
                "targetType":"TEXT",
                "enabled":false
            },
            {
                "sourceName":"properties_siteConfig_push_kind",
                "targetName":"site_config_push_kind",
                "targetType":"TEXT",
                "enabled":false
            },
            {
                "sourceName":"properties_siteConfig_push_name",
                "targetName":"site_config_push_name",
                "targetType":"TEXT",
                "enabled":false
            },
            {
                "sourceName":"properties_siteConfig_push_type",
                "targetName":"site_config_push_type",
                "targetType":"TEXT",
                "enabled":false
            },
            {
                "sourceName":"properties_siteConfig_pythonVersion",
                "targetName":"site_config_python_version",
                "targetType":"TEXT",
                "enabled":false
            },
            {
                "sourceName":"properties_siteConfig_remoteDebuggingEnabled",
                "targetName":"site_config_remote_debugging_enabled",
                "targetType":"TEXT",
                "enabled":false
            },
            {
                "sourceName":"properties_siteConfig_remoteDebuggingVersion",
                "targetName":"site_config_remote_debugging_version",
                "targetType":"TEXT",
                "enabled":false
            },
            {
                "sourceName":"properties_siteConfig_requestTracingEnabled",
                "targetName":"site_config_request_tracing_enabled",
                "targetType":"TEXT",
                "enabled":false
            },
            {
                "sourceName":"properties_siteConfig_requestTracingExpirationTime",
                "targetName":"site_config_request_tracing_expiration_time",
                "targetType":"TEXT",
                "enabled":false
            },
            {
                "sourceName":"properties_siteConfig_scmIpSecurityRestrictions",
                "targetName":"site_config_scm_ip_security_restrictions",
                "targetType":"TEXT",
                "enabled":false
            },
            {
                "sourceName":"properties_siteConfig_scmIpSecurityRestrictionsUseMain",
                "targetName":"site_config_scm_ip_security_restrictions_use_main",
                "targetType":"TEXT",
                "enabled":false
            },
            {
                "sourceName":"properties_siteConfig_scmIpSecurityRestrictions_action",
                "targetName":"site_config_scm_ip_security_restrictions_action",
                "targetType":"TEXT",
                "enabled":false
            },
            {
                "sourceName":"properties_siteConfig_scmIpSecurityRestrictions_description",
                "targetName":"site_config_scm_ip_security_restrictions_description",
                "targetType":"TEXT",
                "enabled":false
            },
            {
                "sourceName":"properties_siteConfig_scmIpSecurityRestrictions_headers",
                "targetName":"site_config_scm_ip_security_restrictions_headers",
                "targetType":"TEXT",
                "enabled":false
            },
            {
                "sourceName":"properties_siteConfig_scmIpSecurityRestrictions_ipAddress",
                "targetName":"site_config_scm_ip_security_restrictions_ip_address",
                "targetType":"TEXT",
                "enabled":false
            },
            {
                "sourceName":"properties_siteConfig_scmIpSecurityRestrictions_name",
                "targetName":"site_config_scm_ip_security_restrictions_name",
                "targetType":"TEXT",
                "enabled":false
            },
            {
                "sourceName":"properties_siteConfig_scmIpSecurityRestrictions_priority",
                "targetName":"site_config_scm_ip_security_restrictions_priority",
                "targetType":"INTEGER",
                "enabled":false
            },
            {
                "sourceName":"properties_siteConfig_scmIpSecurityRestrictions_subnetMask",
                "targetName":"site_config_scm_ip_security_restrictions_subnet_mask",
                "targetType":"TEXT",
                "enabled":false
            },
            {
                "sourceName":"properties_siteConfig_scmIpSecurityRestrictions_subnetTrafficTag",
                "targetName":"site_config_scm_ip_security_restrictions_subnet_traffic_tag",
                "targetType":"INTEGER",
                "enabled":false
            },
            {
                "sourceName":"properties_siteConfig_scmIpSecurityRestrictions_tag",
                "targetName":"site_config_scm_ip_security_restrictions_tag",
                "targetType":"TEXT",
                "enabled":false
            },
            {
                "sourceName":"properties_siteConfig_scmIpSecurityRestrictions_vnetSubnetResourceId",
                "targetName":"site_config_scm_ip_security_restrictions_vnet_subnet_resource_id",
                "targetType":"TEXT",
                "enabled":false
            },
            {
                "sourceName":"properties_siteConfig_scmIpSecurityRestrictions_vnetTrafficTag",
                "targetName":"site_config_scm_ip_security_restrictions_vnet_traffic_tag",
                "targetType":"INTEGER",
                "enabled":false
            },
            {
                "sourceName":"properties_siteConfig_scmMinTlsVersion",
                "targetName":"site_config_scm_min_tls_version",
                "targetType":"TEXT",
                "enabled":false
            },
            {
                "sourceName":"properties_siteConfig_scmType",
                "targetName":"site_config_scm_type",
                "targetType":"TEXT",
                "enabled":false
            },
            {
                "sourceName":"properties_siteConfig_tracingOptions",
                "targetName":"site_config_tracing_options",
                "targetType":"TEXT",
                "enabled":false
            },
            {
                "sourceName":"properties_siteConfig_use32BitWorkerProcess",
                "targetName":"site_config_use32_bit_worker_process",
                "targetType":"TEXT",
                "enabled":false
            },
            {
                "sourceName":"properties_siteConfig_virtualApplications",
                "targetName":"site_config_virtual_applications",
                "targetType":"TEXT",
                "enabled":false
            },
            {
                "sourceName":"properties_siteConfig_virtualApplications_physicalPath",
                "targetName":"site_config_virtual_applications_physical_path",
                "targetType":"TEXT",
                "enabled":false
            },
            {
                "sourceName":"properties_siteConfig_virtualApplications_preloadEnabled",
                "targetName":"site_config_virtual_applications_preload_enabled",
                "targetType":"TEXT",
                "enabled":false
            },
            {
                "sourceName":"properties_siteConfig_virtualApplications_virtualDirectories",
                "targetName":"site_config_virtual_applications_virtual_directories",
                "targetType":"TEXT",
                "enabled":false
            },
            {
                "sourceName":"properties_siteConfig_virtualApplications_virtualDirectories_physicalPath",
                "targetName":"site_config_virtual_applications_virtual_directories_physical_path",
                "targetType":"TEXT",
                "enabled":false
            },
            {
                "sourceName":"properties_siteConfig_virtualApplications_virtualDirectories_virtualPath",
                "targetName":"site_config_virtual_applications_virtual_directories_virtual_path",
                "targetType":"TEXT",
                "enabled":false
            },
            {
                "sourceName":"properties_siteConfig_virtualApplications_virtualPath",
                "targetName":"site_config_virtual_applications_virtual_path",
                "targetType":"TEXT",
                "enabled":false
            },
            {
                "sourceName":"properties_siteConfig_vnetName",
                "targetName":"site_config_vnet_name",
                "targetType":"TEXT",
                "enabled":false
            },
            {
                "sourceName":"properties_siteConfig_vnetPrivatePortsCount",
                "targetName":"site_config_vnet_private_ports_count",
                "targetType":"INTEGER",
                "enabled":false
            },
            {
                "sourceName":"properties_siteConfig_vnetRouteAllEnabled",
                "targetName":"site_config_vnet_route_all_enabled",
                "targetType":"TEXT",
                "enabled":false
            },
            {
                "sourceName":"properties_siteConfig_webSocketsEnabled",
                "targetName":"site_config_web_sockets_enabled",
                "targetType":"TEXT",
                "enabled":false
            },
            {
                "sourceName":"properties_siteConfig_websiteTimeZone",
                "targetName":"site_config_website_time_zone",
                "targetType":"TEXT",
                "enabled":false
            },
            {
                "sourceName":"properties_siteConfig_windowsFxVersion",
                "targetName":"site_config_windows_fx_version",
                "targetType":"TEXT",
                "enabled":false
            },
            {
                "sourceName":"properties_siteConfig_xManagedServiceIdentityId",
                "targetName":"site_config_x_managed_service_identity_id",
                "targetType":"INTEGER",
                "enabled":false
            },
            {
                "sourceName":"properties_slotSwapStatus",
                "targetName":"slot_swap_status",
                "targetType":"TEXT",
                "enabled":true
            },
            {
                "sourceName":"properties_slotSwapStatus_destinationSlotName",
                "targetName":"slot_swap_status_destination_slot_name",
                "targetType":"TEXT",
                "enabled":false
            },
            {
                "sourceName":"properties_slotSwapStatus_sourceSlotName",
                "targetName":"slot_swap_status_source_slot_name",
                "targetType":"TEXT",
                "enabled":false
            },
            {
                "sourceName":"properties_slotSwapStatus_timestampUtc",
                "targetName":"slot_swap_status_timestamp_utc",
                "targetType":"TEXT",
                "enabled":false
            },
            {
                "sourceName":"properties_state",
                "targetName":"state",
                "targetType":"TEXT",
                "enabled":true
            },
            {
                "sourceName":"properties_storageAccountRequired",
                "targetName":"storage_account_required",
                "targetType":"TEXT",
                "enabled":true
            },
            {
                "sourceName":"properties_suspendedTill",
                "targetName":"suspended_till",
                "targetType":"TEXT",
                "enabled":true
            },
            {
                "sourceName":"properties_targetSwapSlot",
                "targetName":"target_swap_slot",
                "targetType":"TEXT",
                "enabled":true
            },
            {
                "sourceName":"properties_trafficManagerHostNames",
                "targetName":"traffic_manager_host_names",
                "targetType":"TEXT",
                "enabled":true
            },
            {
                "sourceName":"properties_usageState",
                "targetName":"usage_state",
                "targetType":"TEXT",
                "enabled":true
            },
            {
                "sourceName":"properties_virtualNetworkSubnetId",
                "targetName":"virtual_network_subnet_id",
                "targetType":"TEXT",
                "enabled":true
            },
            {
                "sourceName":"tags",
                "targetName":"tags",
                "targetType":"TEXT",
                "enabled":true
            },
            {
                "sourceName":"type",
                "targetName":"type",
                "targetType":"TEXT",
                "enabled":true
            }
        ]
    }
}
